Metadata-Version: 2.1
Name: id-mapper-client
Version: 1.3.0
Summary: Client for Identifier Mapper
Home-page: https://github.com/StrongMind/id-mapper-client
Author: team-platform
Author-email: cinnamon@strongmind.com
License: UNKNOWN
Platform: UNKNOWN
